arca/__init__.py
arca/files.py
arca/utilities.py
arca/base/__init__.py
arca/base/bot.py
arca/base/bot_config.py
arca/base/cog.py
arca/base/cog_config.py
arca/discord/__init__.py
arca/discord/decorators.py
arca/discord/slash_commands.py
arca/discord/utilities.py
arca/ext/__init__.py
arca/ext/logs.py
arca/ext/database/__init__.py
arca/ext/database/base.py
arca/ext/database/imports.py
arca/ext/database/tools.py
arca/internal/__init__.py
arca/internal/config_parser.py
arcacog-0.2.0.dist-info/LICENSE
arcacog-0.2.0.dist-info/METADATA
arcacog-0.2.0.dist-info/WHEEL
arcacog-0.2.0.dist-info/top_level.txt
arcacog-0.2.0.dist-info/RECORD
