Metadata-Version: 2.1
Name: arcacog
Version: 0.2.0
Summary: A package to build cogs for Arca
Home-page: https://github.com/nwithan8/arcacog
Author: Nate Harris
Author-email: n8gr8gbln@gmail.com
License: GNU General Public License v3 (GPLv3)
Download-URL: https://github.com/nwithan8/arcacog/archive/refs/tags/0.2.0.tar.gz
Keywords: Discord,bot,cogs,base,Arca
Platform: UNKNOWN
Classifier: License :: OSI Approved :: GNU General Public License v3 (GPLv3)
Classifier: Development Status :: 4 - Beta
Classifier: Intended Audience :: Developers
Classifier: Topic :: Software Development :: Build Tools
Classifier: Programming Language :: Python :: 3
Classifier: Programming Language :: Python :: 3.8
Classifier: Programming Language :: Python :: 3.9
Classifier: Programming Language :: Python :: 3.10
Classifier: Topic :: Multimedia
Classifier: Topic :: Internet :: WWW/HTTP
Classifier: Operating System :: OS Independent
Requires-Python: >=3.8, <4
Requires-Dist: base
